{"city":{"id":484972,"name":"Syzran","coord":{"lon":48.468102,"lat":53.158501},"country":"RU","population":0,"sys":{"population":0}},"cod":"200","message":0.0327,"cnt":40,"list":[{"dt":1473962400,"main":{"temp":8.35,"temp_min":8.35,"temp_max":8.35,"pressure":1002.12,"sea_level":1018.34,"grnd_level":1002.12,"humidity":97,"temp_kf":0},"weather":[{"id":500,"main":"Rain","description":"легкий дождь","icon":"10n"}],"clouds":{"all":48},"wind":{"speed":4.21,"deg":303.001},"rain":{"3h":0.145},"sys":{"pod":"n"},"dt_txt":"2016-09-15 18:00:00"},{"dt":1473973200,"main":{"temp":7.74,"temp_min":7.74,"temp_max":7.74,"pressure":1002.12,"sea_level":1018.42,"grnd_level":1002.12,"humidity":100,"temp_kf":0},"weather":[{"id":500,"main":"Rain","description":"легкий дождь","icon":"10n"}],"clouds":{"all":80},"wind":{"speed":4.91,"deg":309.002},"rain":{"3h":0.585},"sys":{"pod":"n"},"dt_txt":"2016-09-15 21:00:00"},{"dt":1473984000,"main":{"temp":8.01,"temp_min":8.01,"temp_max":8.01,"pressure":1002.55,"sea_level":1018.91,"grnd_level":1002.55,"humidity":100,"temp_kf":0},"weather":[{"id":500,"main":"Rain","description":"легкий дождь","icon":"10n"}],"clouds":{"all":64},"wind":{"speed":4.41,"deg":314.514},"rain":{"3h":0.835},"sys":{"pod":"n"},"dt_txt":"2016-09-16 00:00:00"},{"dt":1473994800,"main":{"temp":7.25,"temp_min":7.25,"temp_max":7.25,"pressure":1003.59,"sea_level":1019.92,"grnd_level":1003.59,"humidity":100,"temp_kf":0},"weather":[{"id":500,"main":"Rain","description":"легкий дождь","icon":"10d"}],"clouds":{"all":24},"wind":{"speed":4.47,"deg":306.506},"rain":{"3h":0.525},"sys":{"pod":"d"},"dt_txt":"2016-09-16 03:00:00"},{"dt":1474005600,"main":{"temp":10.23,"temp_min":10.23,"temp_max":10.23,"pressure":1004.25,"sea_level":1020.61,"grnd_level":1004.25,"humidity":97,"temp_kf":0},"weather":[{"id":500,"main":"Rain","description":"легкий дождь","icon":"10d"}],"clouds":{"all":36},"wind":{"speed":4.11,"deg":304.503},"rain":{"3h":0.06},"sys":{"pod":"d"},"dt_txt":"2016-09-16 06:00:00"},{"dt":1474016400,"main":{"temp":12.58,"temp_min":12.58,"temp_max":12.58,"pressure":1004.47,"sea_level":1020.58,"grnd_level":1004.47,"humidity":79,"temp_kf":0},"weather":[{"id":500,"main":"Rain","description":"легкий дождь","icon":"10d"}],"clouds":{"all":32},"wind":{"speed":4.32,"deg":302.001},"rain":{"3h":0.01},"sys":{"pod":"d"},"dt_txt":"2016-09-16 09:00:00"},{"dt":1474027200,"main":{"temp":12.28,"temp_min":12.28,"temp_max":12.28,"pressure":1004.62,"sea_level":1020.65,"grnd_level":1004.62,"humidity":75,"temp_kf":0},"weather":[{"id":500,"main":"Rain","description":"легкий дождь","icon":"10d"}],"clouds":{"all":76},"wind":{"speed":4.17,"deg":295.5},"rain":{"3h":0.03},"sys":{"pod":"d"},"dt_txt":"2016-09-16 12:00:00"},{"dt":1474038000,"main":{"temp":10.48,"temp_min":10.48,"temp_max":10.48,"pressure":1004.81,"sea_level":1020.97,"grnd_level":1004.81,"humidity":79,"temp_kf":0},"weather":[{"id":803,"main":"Clouds","description":"пасмурно","icon":"04n"}],"clouds":{"all":76},"wind":{"speed":2.11,"deg":274.5},"rain":{},"sys":{"pod":"n"},"dt_txt":"2016-09-16 15:00:00"},{"dt":1474048800,"main":{"temp":8.65,"temp_min":8.65,"temp_max":8.65,"pressure":1004.85,"sea_level":1021.04,"grnd_level":1004.85,"humidity":90,"temp_kf":0},"weather":[{"id":500,"main":"Rain","description":"легкий дождь","icon":"10n"}],"clouds":{"all":88},"wind":{"speed":2.36,"deg":259.005},"rain":{"3h":0.02},"sys":{"pod":"n"},"dt_txt":"2016-09-16 18:00:00"},{"dt":1474059600,"main":{"temp":7.13,"temp_min":7.13,"temp_max":7.13,"pressure":1004.12,"sea_level":1020.39,"grnd_level":1004.12,"humidity":100,"temp_kf":0},"weather":[{"id":500,"main":"Rain","description":"легкий дождь","icon":"10n"}],"clouds":{"all":92},"wind":{"speed":1.46,"deg":229.502},"rain":{"3h":0.005},"sys":{"pod":"n"},"dt_txt":"2016-09-16 21:00:00"},{"dt":1474070400,"main":{"temp":6.43,"temp_min":6.43,"temp_max":6.43,"pressure":1003.6,"sea_level":1019.96,"grnd_level":1003.6,"humidity":100,"temp_kf":0},"weather":[{"id":500,"main":"Rain","description":"легкий дождь","icon":"10n"}],"clouds":{"all":88},"wind":{"speed":1.21,"deg":165.006},"rain":{"3h":0.22},"sys":{"pod":"n"},"dt_txt":"2016-09-17 00:00:00"},{"dt":1474081200,"main":{"temp":7.19,"temp_min":7.19,"temp_max":7.19,"pressure":1003.16,"sea_level":1019.56,"grnd_level":1003.16,"humidity":100,"temp_kf":0},"weather":[{"id":500,"main":"Rain","description":"легкий дождь","icon":"10d"}],"clouds":{"all":80},"wind":{"speed":1.46,"deg":143.001},"rain":{"3h":0.46},"sys":{"pod":"d"},"dt_txt":"2016-09-17 03:00:00"},{"dt":1474092000,"main":{"temp":9.54,"temp_min":9.54,"temp_max":9.54,"pressure":1002.91,"sea_level":1019.18,"grnd_level":1002.91,"humidity":100,"temp_kf":0},"weather":[{"id":500,"main":"Rain","description":"легкий дождь","icon":"10d"}],"clouds":{"all":92},"wind":{"speed":1.8,"deg":163},"rain":{"3h":0.19},"sys":{"pod":"d"},"dt_txt":"2016-09-17 06:00:00"},{"dt":1474102800,"main":{"temp":10.51,"temp_min":10.51,"temp_max":10.51,"pressure":1002.52,"sea_level":1018.72,"grnd_level":1002.52,"humidity":100,"temp_kf":0},"weather":[{"id":500,"main":"Rain","description":"легкий дождь","icon":"10d"}],"clouds":{"all":92},"wind":{"speed":1.62,"deg":123.001},"rain":{"3h":0.89},"sys":{"pod":"d"},"dt_txt":"2016-09-17 09:00:00"},{"dt":1474113600,"main":{"temp":10.36,"temp_min":10.36,"temp_max":10.36,"pressure":1002.73,"sea_level":1018.83,"grnd_level":1002.73,"humidity":100,"temp_kf":0},"weather":[{"id":501,"main":"Rain","description":"дождь","icon":"10d"}],"clouds":{"all":92},"wind":{"speed":1.66,"deg":357.005},"rain":{"3h":3.23},"sys":{"pod":"d"},"dt_txt":"2016-09-17 12:00:00"},{"dt":1474124400,"main":{"temp":9.35,"temp_min":9.35,"temp_max":9.35,"pressure":1003.33,"sea_level":1019.51,"grnd_level":1003.33,"humidity":100,"temp_kf":0},"weather":[{"id":500,"main":"Rain","description":"легкий дождь","icon":"10n"}],"clouds":{"all":64},"wind":{"speed":1.51,"deg":326.005},"rain":{"3h":0.8},"sys":{"pod":"n"},"dt_txt":"2016-09-17 15:00:00"},{"dt":1474135200,"main":{"temp":6.03,"temp_min":6.03,"temp_max":6.03,"pressure":1003.83,"sea_level":1020.02,"grnd_level":1003.83,"humidity":100,"temp_kf":0},"weather":[{"id":500,"main":"Rain","description":"легкий дождь","icon":"10n"}],"clouds":{"all":20},"wind":{"speed":2.55,"deg":309.002},"rain":{"3h":0.02},"sys":{"pod":"n"},"dt_txt":"2016-09-17 18:00:00"},{"dt":1474146000,"main":{"temp":4.89,"temp_min":4.89,"temp_max":4.89,"pressure":1003.71,"sea_level":1019.97,"grnd_level":1003.71,"humidity":100,"temp_kf":0},"weather":[{"id":801,"main":"Clouds","description":"облачно","icon":"02n"}],"clouds":{"all":12},"wind":{"speed":3.21,"deg":311.001},"rain":{},"sys":{"pod":"n"},"dt_txt":"2016-09-17 21:00:00"},{"dt":1474156800,"main":{"temp":4.95,"temp_min":4.95,"temp_max":4.95,"pressure":1004.09,"sea_level":1020.38,"grnd_level":1004.09,"humidity":100,"temp_kf":0},"weather":[{"id":802,"main":"Clouds","description":"слегка облачно","icon":"03n"}],"clouds":{"all":32},"wind":{"speed":2.87,"deg":288.501},"rain":{},"sys":{"pod":"n"},"dt_txt":"2016-09-18 00:00:00"},{"dt":1474167600,"main":{"temp":4.79,"temp_min":4.79,"temp_max":4.79,"pressure":1004.37,"sea_level":1020.84,"grnd_level":1004.37,"humidity":100,"temp_kf":0},"weather":[{"id":800,"main":"Clear","description":"ясно","icon":"02d"}],"clouds":{"all":8},"wind":{"speed":3.02,"deg":295.002},"rain":{},"sys":{"pod":"d"},"dt_txt":"2016-09-18 03:00:00"},{"dt":1474178400,"main":{"temp":10.18,"temp_min":10.18,"temp_max":10.18,"pressure":1004.7,"sea_level":1020.96,"grnd_level":1004.7,"humidity":100,"temp_kf":0},"weather":[{"id":500,"main":"Rain","description":"легкий дождь","icon":"10d"}],"clouds":{"all":24},"wind":{"speed":2.56,"deg":285.509},"rain":{"3h":0.02},"sys":{"pod":"d"},"dt_txt":"2016-09-18 06:00:00"},{"dt":1474189200,"main":{"temp":13.18,"temp_min":13.18,"temp_max":13.18,"pressure":1004.18,"sea_level":1020.28,"grnd_level":1004.18,"humidity":83,"temp_kf":0},"weather":[{"id":802,"main":"Clouds","description":"слегка облачно","icon":"03d"}],"clouds":{"all":36},"wind":{"speed":3.46,"deg":254},"rain":{},"sys":{"pod":"d"},"dt_txt":"2016-09-18 09:00:00"},{"dt":1474200000,"main":{"temp":12.97,"temp_min":12.97,"temp_max":12.97,"pressure":1004.25,"sea_level":1020.43,"grnd_level":1004.25,"humidity":77,"temp_kf":0},"weather":[{"id":500,"main":"Rain","description":"легкий дождь","icon":"10d"}],"clouds":{"all":44},"wind":{"speed":4.16,"deg":279.015},"rain":{"3h":0.0125},"sys":{"pod":"d"},"dt_txt":"2016-09-18 12:00:00"},{"dt":1474210800,"main":{"temp":10.68,"temp_min":10.68,"temp_max":10.68,"pressure":1004.88,"sea_level":1021.06,"grnd_level":1004.88,"humidity":85,"temp_kf":0},"weather":[{"id":500,"main":"Rain","description":"легкий дождь","icon":"10n"}],"clouds":{"all":56},"wind":{"speed":4.41,"deg":283.502},"rain":{"3h":0.125},"sys":{"pod":"n"},"dt_txt":"2016-09-18 15:00:00"},{"dt":1474221600,"main":{"temp":7.9,"temp_min":7.9,"temp_max":7.9,"pressure":1005.31,"sea_level":1021.53,"grnd_level":1005.31,"humidity":99,"temp_kf":0},"weather":[{"id":500,"main":"Rain","description":"легкий дождь","icon":"10n"}],"clouds":{"all":8},"wind":{"speed":3.73,"deg":282.503},"rain":{"3h":0.0125},"sys":{"pod":"n"},"dt_txt":"2016-09-18 18:00:00"},{"dt":1474232400,"main":{"temp":6.11,"temp_min":6.11,"temp_max":6.11,"pressure":1005.03,"sea_level":1021.35,"grnd_level":1005.03,"humidity":100,"temp_kf":0},"weather":[{"id":800,"main":"Clear","description":"ясно","icon":"02n"}],"clouds":{"all":8},"wind":{"speed":3.66,"deg":273.003},"rain":{},"sys":{"pod":"n"},"dt_txt":"2016-09-18 21:00:00"},{"dt":1474243200,"main":{"temp":5.2,"temp_min":5.2,"temp_max":5.2,"pressure":1004.92,"sea_level":1021.34,"grnd_level":1004.92,"humidity":100,"temp_kf":0},"weather":[{"id":801,"main":"Clouds","description":"облачно","icon":"02n"}],"clouds":{"all":12},"wind":{"speed":3.66,"deg":261.504},"rain":{},"sys":{"pod":"n"},"dt_txt":"2016-09-19 00:00:00"},{"dt":1474254000,"main":{"temp":6.07,"temp_min":6.07,"temp_max":6.07,"pressure":1005.06,"sea_level":1021.44,"grnd_level":1005.06,"humidity":100,"temp_kf":0},"weather":[{"id":500,"main":"Rain","description":"легкий дождь","icon":"10d"}],"clouds":{"all":36},"wind":{"speed":3.86,"deg":255.508},"rain":{"3h":0.05},"sys":{"pod":"d"},"dt_txt":"2016-09-19 03:00:00"},{"dt":1474264800,"main":{"temp":10.01,"temp_min":10.01,"temp_max":10.01,"pressure":1005.25,"sea_level":1021.57,"grnd_level":1005.25,"humidity":94,"temp_kf":0},"weather":[{"id":500,"main":"Rain","description":"легкий дождь","icon":"10d"}],"clouds":{"all":68},"wind":{"speed":4.81,"deg":262.005},"rain":{"3h":0.125},"sys":{"pod":"d"},"dt_txt":"2016-09-19 06:00:00"},{"dt":1474275600,"main":{"temp":11.38,"temp_min":11.38,"temp_max":11.38,"pressure":1005.6,"sea_level":1021.75,"grnd_level":1005.6,"humidity":83,"temp_kf":0},"weather":[{"id":500,"main":"Rain","description":"легкий дождь","icon":"10d"}],"clouds":{"all":44},"wind":{"speed":5.57,"deg":268.5},"rain":{"3h":0.025},"sys":{"pod":"d"},"dt_txt":"2016-09-19 09:00:00"},{"dt":1474286400,"main":{"temp":11.49,"temp_min":11.49,"temp_max":11.49,"pressure":1006.04,"sea_level":1022.22,"grnd_level":1006.04,"humidity":80,"temp_kf":0},"weather":[{"id":500,"main":"Rain","description":"легкий дождь","icon":"10d"}],"clouds":{"all":76},"wind":{"speed":5.46,"deg":275},"rain":{"3h":0.125},"sys":{"pod":"d"},"dt_txt":"2016-09-19 12:00:00"},{"dt":1474297200,"main":{"temp":10.11,"temp_min":10.11,"temp_max":10.11,"pressure":1006.67,"sea_level":1022.92,"grnd_level":1006.67,"humidity":82,"temp_kf":0},"weather":[{"id":803,"main":"Clouds","description":"пасмурно","icon":"04n"}],"clouds":{"all":56},"wind":{"speed":4.3,"deg":272.501},"rain":{},"sys":{"pod":"n"},"dt_txt":"2016-09-19 15:00:00"},{"dt":1474308000,"main":{"temp":8.55,"temp_min":8.55,"temp_max":8.55,"pressure":1007.4,"sea_level":1023.64,"grnd_level":1007.4,"humidity":88,"temp_kf":0},"weather":[{"id":803,"main":"Clouds","description":"пасмурно","icon":"04n"}],"clouds":{"all":64},"wind":{"speed":3.91,"deg":264.501},"rain":{},"sys":{"pod":"n"},"dt_txt":"2016-09-19 18:00:00"},{"dt":1474318800,"main":{"temp":7.81,"temp_min":7.81,"temp_max":7.81,"pressure":1007.38,"sea_level":1023.68,"grnd_level":1007.38,"humidity":92,"temp_kf":0},"weather":[{"id":804,"main":"Clouds","description":"пасмурно","icon":"04n"}],"clouds":{"all":88},"wind":{"speed":3.67,"deg":260.002},"rain":{},"sys":{"pod":"n"},"dt_txt":"2016-09-19 21:00:00"},{"dt":1474329600,"main":{"temp":7.42,"temp_min":7.42,"temp_max":7.42,"pressure":1007.63,"sea_level":1024.03,"grnd_level":1007.63,"humidity":96,"temp_kf":0},"weather":[{"id":500,"main":"Rain","description":"легкий дождь","icon":"10n"}],"clouds":{"all":56},"wind":{"speed":3.56,"deg":255.502},"rain":{"3h":0.05},"sys":{"pod":"n"},"dt_txt":"2016-09-20 00:00:00"},{"dt":1474340400,"main":{"temp":6.85,"temp_min":6.85,"temp_max":6.85,"pressure":1007.93,"sea_level":1024.31,"grnd_level":1007.93,"humidity":100,"temp_kf":0},"weather":[{"id":500,"main":"Rain","description":"легкий дождь","icon":"10d"}],"clouds":{"all":64},"wind":{"speed":3.21,"deg":251.005},"rain":{"3h":0.025},"sys":{"pod":"d"},"dt_txt":"2016-09-20 03:00:00"},{"dt":1474351200,"main":{"temp":9.75,"temp_min":9.75,"temp_max":9.75,"pressure":1008.21,"sea_level":1024.49,"grnd_level":1008.21,"humidity":84,"temp_kf":0},"weather":[{"id":803,"main":"Clouds","description":"пасмурно","icon":"04d"}],"clouds":{"all":80},"wind":{"speed":3.47,"deg":255.503},"rain":{},"sys":{"pod":"d"},"dt_txt":"2016-09-20 06:00:00"},{"dt":1474362000,"main":{"temp":11.33,"temp_min":11.33,"temp_max":11.33,"pressure":1008.16,"sea_level":1024.38,"grnd_level":1008.16,"humidity":73,"temp_kf":0},"weather":[{"id":803,"main":"Clouds","description":"пасмурно","icon":"04d"}],"clouds":{"all":76},"wind":{"speed":3.86,"deg":249.004},"rain":{},"sys":{"pod":"d"},"dt_txt":"2016-09-20 09:00:00"},{"dt":1474372800,"main":{"temp":12.02,"temp_min":12.02,"temp_max":12.02,"pressure":1007.84,"sea_level":1024.07,"grnd_level":1007.84,"humidity":69,"temp_kf":0},"weather":[{"id":804,"main":"Clouds","description":"пасмурно","icon":"04d"}],"clouds":{"all":88},"wind":{"speed":4.3,"deg":250.501},"rain":{},"sys":{"pod":"d"},"dt_txt":"2016-09-20 12:00:00"},{"dt":1474383600,"main":{"temp":10.68,"temp_min":10.68,"temp_max":10.68,"pressure":1008.01,"sea_level":1024.24,"grnd_level":1008.01,"humidity":70,"temp_kf":0},"weather":[{"id":804,"main":"Clouds","description":"пасмурно","icon":"04n"}],"clouds":{"all":92},"wind":{"speed":3.06,"deg":256.002},"rain":{},"sys":{"pod":"n"},"dt_txt":"2016-09-20 15:00:00"}]}